bin/__init__.py
bin/epbdcalc.py
pyepbd/__init__.py
pyepbd/__main__.py
pyepbd/cli.py
pyepbd/energycalculations.py
pyepbd/inputoutput.py
pyepbd/settings.py
pyepbd/utils.py
pyepbd/examples/broken_input.csv
pyepbd/examples/ejemplo1PV.csv
pyepbd/examples/ejemplo1PV_salida.csv
pyepbd/examples/ejemplo1base.csv
pyepbd/examples/ejemplo1base_salida.csv
pyepbd/examples/ejemplo1xPV.csv
pyepbd/examples/ejemplo1xPV_salida.csv
pyepbd/examples/ejemplo2PVgas.csv
pyepbd/examples/ejemplo2PVgas_salida.csv
pyepbd/examples/ejemplo2xPVgas.csv
pyepbd/examples/ejemplo2xPVgas_salida.csv
pyepbd/examples/ejemplo3PVBdC.csv
pyepbd/examples/ejemplo3PVBdC_salida.csv
pyepbd/examples/ejemplo4cgnfosil.csv
pyepbd/examples/ejemplo4cgnfosil_salida.csv
pyepbd/examples/ejemplo5cgnbiogas.csv
pyepbd/examples/ejemplo5cgnbiogas_salida.csv
pyepbd/examples/ejemplo6K3.csv
pyepbd/examples/ejemplo6K3_salida.csv
pyepbd/examples/factores_paso_20140203.csv
pyepbd/examples/factores_paso_test.csv
pyepbd/test/.coveragerc
pyepbd/test/__init__.py
pyepbd/test/test_pyepbd.py
pyepbd-6.1.dist-info/DESCRIPTION.rst
pyepbd-6.1.dist-info/METADATA
pyepbd-6.1.dist-info/RECORD
pyepbd-6.1.dist-info/WHEEL
pyepbd-6.1.dist-info/entry_points.txt
pyepbd-6.1.dist-info/metadata.json
pyepbd-6.1.dist-info/top_level.txt
