Metadata-Version: 2.0
Name: pyepbd
Version: 6.1
Summary: Cálculo de la eficiencia energética según ISO/DIS 52000-1:2015
Home-page: https://github.com/pachi/epbdcalc
Author: Rafael Villar Burke, Daniel Jiménez González
Author-email: pachi@ietcc.csic.es
License: MIT
Keywords: energía,edificación,CTE,energy,buildings
Platform: UNKNOWN
Classifier: Development Status :: 5 - Production/Stable
Classifier: Intended Audience :: Science/Research
Classifier: Topic :: Scientific/Engineering
Classifier: License :: OSI Approved :: MIT License
Classifier: Programming Language :: Python :: 2
Classifier: Programming Language :: Python :: Implementation :: CPython
Classifier: Environment :: Console
Classifier: Operating System :: OS Independent
Provides-Extra: test
Requires-Dist: pytest; extra == 'test'
Requires-Dist: pytest-cov; extra == 'test'
